agora/__init__.py
agora/error.py
agora/keys.py
agora/utils.py
agora/version.py
agora/cache/__init__.py
agora/cache/cache.py
agora/client/__init__.py
agora/client/client.py
agora/client/environment.py
agora/client/internal.py
agora/client/account/__init__.py
agora/client/account/resolution.py
agora/model/__init__.py
agora/model/account.py
agora/model/creation.py
agora/model/earn.py
agora/model/invoice.py
agora/model/memo.py
agora/model/payment.py
agora/model/result.py
agora/model/transaction.py
agora/model/transaction_type.py
agora/model/utils.py
agora/retry/__init__.py
agora/retry/backoff.py
agora/retry/strategy.py
agora/solana/__init__.py
agora/solana/address.py
agora/solana/commitment.py
agora/solana/instruction.py
agora/solana/shortvec.py
agora/solana/transaction.py
agora/solana/memo/__init__.py
agora/solana/memo/program.py
agora/solana/system/__init__.py
agora/solana/system/program.py
agora/solana/token/__init__.py
agora/solana/token/associated.py
agora/solana/token/program.py
agora/webhook/__init__.py
agora/webhook/create_account.py
agora/webhook/events.py
agora/webhook/handler.py
agora/webhook/sign_transaction.py
kin_sdk_v2-0.7.1.dist-info/LICENSE.md
kin_sdk_v2-0.7.1.dist-info/METADATA
kin_sdk_v2-0.7.1.dist-info/WHEEL
kin_sdk_v2-0.7.1.dist-info/top_level.txt
kin_sdk_v2-0.7.1.dist-info/RECORD
