Metadata-Version: 2.1
Name: kin-sdk-v2
Version: 0.7.1
Summary: Kin SDK for Python
Home-page: https://github.com/kinecosystem/kin-python
Author: Kik Engineering
Author-email: engineering@kik.com
License: MIT
Keywords: kin,agora,stellar,blockchain,cryptocurrency
Platform: UNKNOWN
Classifier: License :: OSI Approved :: MIT License
Classifier: Intended Audience :: Developers
Classifier: Topic :: Software Development :: Libraries :: Python Modules
Classifier: Programming Language :: Python
Classifier: Programming Language :: Python :: 3
Requires-Python: >=3.6
License-File: LICENSE.md
Requires-Dist: grpcio (==1.34.1)
Requires-Dist: agora-api (==0.26.0)
Requires-Dist: kin-base (==1.4.1)
Requires-Dist: pure25519 (==0.0.1)
Requires-Dist: protobuf (==3.12.2)
Requires-Dist: pynacl (==1.4.0)
Requires-Dist: base58 (==2.0.1)
Requires-Dist: ed25519 (==1.4) ; sys_platform != "win32" and sys_platform != "cygwin"
